aitalk/__init__.py
aitalk/display.py
aitalk/main_file.py
aitalk-0.1.0.dist-info/METADATA
aitalk-0.1.0.dist-info/WHEEL
aitalk-0.1.0.dist-info/top_level.txt
aitalk-0.1.0.dist-info/RECORD
