Metadata-Version: 2.1
Name: aitalk
Version: 0.1.0
Summary: A speech assistant package
Author: Imane Mtq
Author-email: imottaqi@archipel.group
Classifier: Programming Language :: Python :: 3
Classifier: License :: OSI Approved :: MIT License
Classifier: Operating System :: Microsoft :: Windows
Requires-Dist: pygame ==2.5.2
Requires-Dist: aiohttp ==3.9.5
Requires-Dist: aiosignal ==1.3.1
Requires-Dist: alembic ==1.13.1
Requires-Dist: aniso8601 ==9.0.1
Requires-Dist: annotated-types ==0.6.0
Requires-Dist: anyio ==4.3.0
Requires-Dist: apispec ==5.2.2
Requires-Dist: apispec-webframeworks ==0.5.2
Requires-Dist: arrow ==1.3.0
Requires-Dist: asttokens ==2.4.1
Requires-Dist: async-timeout ==4.0.3
Requires-Dist: attrs ==23.2.0
Requires-Dist: Automat ==22.10.0
Requires-Dist: bidict ==0.23.1
Requires-Dist: binaryornot ==0.4.4
Requires-Dist: blinker ==1.7.0
Requires-Dist: certifi ==2024.2.2
Requires-Dist: cffi ==1.16.0
Requires-Dist: chardet ==5.2.0
Requires-Dist: charset-normalizer ==3.3.2
Requires-Dist: click ==8.1.7
Requires-Dist: cloudpickle ==3.0.0
Requires-Dist: colorama ==0.4.6
Requires-Dist: constantly ==23.10.4
Requires-Dist: cookiecutter ==2.1.1
Requires-Dist: dask ==2024.4.2
Requires-Dist: dataclasses-json ==0.6.5
Requires-Dist: decorator ==5.1.1
Requires-Dist: deepdiff ==6.2.3
Requires-Dist: deepgram-sdk ==3.1.4
Requires-Dist: distributed ==2024.4.2
Requires-Dist: distro ==1.9.0
Requires-Dist: dnspython ==2.6.1
Requires-Dist: elevenlabs ==0.2.27
Requires-Dist: et-xmlfile ==1.1.0
Requires-Dist: exceptiongroup ==1.2.1
Requires-Dist: executing ==2.0.1
Requires-Dist: Flask ==3.0.3
Requires-Dist: Flask-Cors ==4.0.0
Requires-Dist: flask-marshmallow ==0.14.0
Requires-Dist: Flask-Migrate ==3.1.0
Requires-Dist: Flask-RESTful ==0.3.10
Requires-Dist: Flask-SocketIO ==5.3.6
Requires-Dist: Flask-SQLAlchemy ==3.1.1
Requires-Dist: frozenlist ==1.4.1
Requires-Dist: fsspec ==2024.3.1
Requires-Dist: gevent ==23.9.1
Requires-Dist: gevent-websocket ==0.10.1
Requires-Dist: gitignore-parser ==0.1.11
Requires-Dist: greenlet ==3.0.3
Requires-Dist: groq ==0.5.0
Requires-Dist: h11 ==0.14.0
Requires-Dist: httpcore ==1.0.5
Requires-Dist: httpx ==0.27.0
Requires-Dist: hyperlink ==21.0.0
Requires-Dist: idna ==3.7
Requires-Dist: importlib-metadata ==7.1.0
Requires-Dist: incremental ==22.10.0
Requires-Dist: ipython ==8.23.0
Requires-Dist: itsdangerous ==2.2.0
Requires-Dist: jedi ==0.19.1
Requires-Dist: Jinja2 ==3.1.3
Requires-Dist: jinja2-time ==0.2.0
Requires-Dist: jsonpatch ==1.33
Requires-Dist: jsonpointer ==2.4
Requires-Dist: kthread ==0.2.3
Requires-Dist: langchain ==0.1.14
Requires-Dist: langchain-core ==0.1.46
Requires-Dist: langchain-groq ==0.0.1
Requires-Dist: langsmith ==0.1.52
Requires-Dist: locket ==1.0.0
Requires-Dist: Mako ==1.3.3
Requires-Dist: Markdown ==3.6
Requires-Dist: MarkupSafe ==2.1.5
Requires-Dist: marshmallow ==3.21.1
Requires-Dist: marshmallow-sqlalchemy ==0.28.1
Requires-Dist: matplotlib-inline ==0.1.7
Requires-Dist: modin ==0.29.0
Requires-Dist: msgpack ==1.0.8
Requires-Dist: multidict ==6.0.5
Requires-Dist: mypy-extensions ==1.0.0
Requires-Dist: networkx ==2.8.8
Requires-Dist: numpy ==1.26.4
Requires-Dist: openai ==1.4.0
Requires-Dist: openpyxl ==3.1.2
Requires-Dist: ordered-set ==4.1.0
Requires-Dist: orjson ==3.10.1
Requires-Dist: packaging ==23.2
Requires-Dist: pandas ==2.2.2
Requires-Dist: parso ==0.8.4
Requires-Dist: partd ==1.4.1
Requires-Dist: passlib ==1.7.4
Requires-Dist: pip ==24.0
Requires-Dist: prompt-toolkit ==3.0.43
Requires-Dist: psutil ==5.9.8
Requires-Dist: pure-eval ==0.2.2
Requires-Dist: pyarrow ==10.0.1
Requires-Dist: PyAudio ==0.2.14
Requires-Dist: pycparser ==2.22
Requires-Dist: pydantic ==2.7.1
Requires-Dist: pydantic-core ==2.18.2
Requires-Dist: Pygments ==2.17.2
Requires-Dist: pymongo ==4.7.0
Requires-Dist: python-dateutil ==2.9.0.post0
Requires-Dist: python-dotenv ==1.0.0
Requires-Dist: python-engineio ==4.9.0
Requires-Dist: python-slugify ==8.0.4
Requires-Dist: python-socketio ==5.11.2
Requires-Dist: pytz ==2022.1
Requires-Dist: pytz-deprecation-shim ==0.1.0.post0
Requires-Dist: PyYAML ==6.0.1
Requires-Dist: requests ==2.31.0
Requires-Dist: setuptools ==63.2.0
Requires-Dist: simple-websocket ==0.10.1
Requires-Dist: six ==1.16.0
Requires-Dist: sniffio ==1.3.1
Requires-Dist: sortedcontainers ==2.4.0
Requires-Dist: SQLAlchemy ==2.0.29
Requires-Dist: stack-data ==0.6.3
Requires-Dist: taipy ==3.0.0
Requires-Dist: taipy-config ==3.0.0
Requires-Dist: taipy-core ==3.0.0
Requires-Dist: taipy-gui ==3.0.0
Requires-Dist: taipy-rest ==3.0.0
Requires-Dist: taipy-templates ==3.0.0
Requires-Dist: tblib ==3.0.0
Requires-Dist: tenacity ==8.2.3
Requires-Dist: text-unidecode ==1.3
Requires-Dist: toml ==0.10.2
Requires-Dist: toolz ==0.12.1
Requires-Dist: tornado ==6.4
Requires-Dist: tqdm ==4.66.2
Requires-Dist: traitlets ==5.14.3
Requires-Dist: Twisted ==23.10.0
Requires-Dist: twisted-iocpsupport ==1.0.4
Requires-Dist: types-python-dateutil ==2.9.0.20240316
Requires-Dist: typing-extensions ==4.11.0
Requires-Dist: typing-inspect ==0.9.0
Requires-Dist: tzdata ==2024.1
Requires-Dist: tzlocal ==4.3.1
Requires-Dist: urllib3 ==2.2.1
Requires-Dist: verboselogs ==1.7
Requires-Dist: wcwidth ==0.2.13
Requires-Dist: websockets ==12.0
Requires-Dist: Werkzeug ==3.0.2
Requires-Dist: wsproto ==1.2.0
Requires-Dist: yarl ==1.9.4
Requires-Dist: zict ==3.0.0
Requires-Dist: zipp ==3.18.1
Requires-Dist: zope.event ==5.0
Requires-Dist: zope.interface ==6.3
